{
  "strategy": "oracle",
  "globalSwitch": true,
  "expireTime": 60,
  "negativeExpireTime": 60,
  "s": ["i", "c", "cs"],
  "c": [1],
  "aa": [5000],
  "weight": {
    "T": 0.0004,
    "TDE": 0.0012,
    "TI": 0.0006,
    "C": 0.0004,
    "CDE": 0.0012,
    "CI": 0.0006,
    "I": 0.0004,
    "IDE": 0.0012
  },
  "mr": 0.9990,
  "emr": {
    "WESTE": 1.0015,
    "STEWE": 0.9998,
    
    "WEWEE": 0.9,
    "WEEWE": 1.042,

    "WEWST": 0.8,
    "WSTWE": 1.17
  },
  "r": {
    "WEWEE": 1.0017,
    "WEEWE": 0.9998,
    "WEEWST": 1.0002,
    "WEESTE": 1.0015,
    
    "WEWST": 1.0017,
    "WSTWE": 0.9998,
    "WSTWEE": 1.0015,
    "WSTSTE": 1.0015,
    
    "STEWST": 0.9999,
    "STEWEE": 1.0004,
    "STEWE": 0.9998
  }
}
